{
    "cities": [
        {
            "id": "540100",
            "zh": "拉萨",
            "en": "Lasa"
        },
        {
            "id": "540200",
            "zh": "日喀则",
            "en": "Rikaze"
        },
        {
            "id": "540300",
            "zh": "昌都",
            "en": "Changdou"
        },
        {
            "id": "540400",
            "zh": "林芝",
            "en": "Linzhi"
        },
        {
            "id": "540500",
            "zh": "山南",
            "en": "Shannan"
        },
        {
            "id": "540600",
            "zh": "那曲",
            "en": "Naqu"
        },
        {
            "id": "542500",
            "zh": "阿里地区",
            "en": "Alidiqu"
        }
    ]
}